README.md
setup.py
chamferdist/__init__.py
chamferdist/chamfer.py
chamferdist/cutils.h
chamferdist/dispatch.cuh
chamferdist/ext.cpp
chamferdist/index_utils.cuh
chamferdist/knn.cu
chamferdist/knn.h
chamferdist/knn_cpu.cpp
chamferdist/mink.cuh
chamferdist/version.py
chamferdist.egg-info/PKG-INFO
chamferdist.egg-info/SOURCES.txt
chamferdist.egg-info/dependency_links.txt
chamferdist.egg-info/requires.txt
chamferdist.egg-info/top_level.txt