Metadata-Version: 2.1
Name: chamferdist
Version: 1.0.0
Summary: Pytorch Chamfer distance
Home-page: UNKNOWN
License: UNKNOWN
Platform: UNKNOWN
Provides-Extra: dev
